webtest_plus/__init__.py
webtest_plus/app.py
webtest_plus/compat.py
webtest_plus/response.py
webtest_plus-1.0.0.dist-info/DESCRIPTION.rst
webtest_plus-1.0.0.dist-info/METADATA
webtest_plus-1.0.0.dist-info/RECORD
webtest_plus-1.0.0.dist-info/WHEEL
webtest_plus-1.0.0.dist-info/metadata.json
webtest_plus-1.0.0.dist-info/top_level.txt
