Metadata-Version: 2.0
Name: webtest-plus
Version: 1.0.0
Summary: An extension of WebTest with useful extras, including requests-style authentication.
Home-page: https://github.com/sloria/webtest-plus
Author: Steven Loria
Author-email: sloria1@gmail.com
License: Copyright 2017 Steven Loria
Requires-Dist: webtest (>=2.0.9)
